README.md
setup.py
dora_pktest.egg-info/PKG-INFO
dora_pktest.egg-info/SOURCES.txt
dora_pktest.egg-info/dependency_links.txt
dora_pktest.egg-info/top_level.txt
dora_pktest_lib/__init__.py
dora_pktest_lib/multiple.py
dora_pktest_lib/plus.py